[
  {
    "id": 10,
    "status": 0,
    "creationTime": "2021-06-15T11:48:38.8025299",
    "workshopId": 2,
    "childId": 17,
    "userId": "55ac98f3-591f-40b3-8b58-3b46a91215a9"
  },
  {
    "id": 11,
    "status": 0,
    "creationTime": "2021-06-15T11:59:06.0523627",
    "workshopId": 1,
    "childId": 17,
    "userId": "0e84158f-4dd4-4468-952e-d6f699533c1a"
  },
  {
    "id": 12,
    "status": 0,
    "creationTime": "2021-06-15T14:04:55.5404038",
    "workshopId": 2,
    "childId": 19,
    "userId": "0e84158f-4dd4-4468-952e-d6f699533c1a"
  },
  {
    "id": 13,
    "status": 0,
    "creationTime": "2021-06-15T14:05:13.6933244",
    "workshopId": 1,
    "childId": 20,
    "userId": "0e84158f-4dd4-4468-952e-d6f699533c1a"
  },
  {
    "id": 14,
    "status": 0,
    "creationTime": "2021-06-15T20:16:16.8529891",
    "workshopId": 2,
    "childId": 20,
    "userId": "0e84158f-4dd4-4468-952e-d6f699533c1a"
  }
]